{"resources":{"BBDD_Proyecto.sql":{"default-schema":"public","default-datasource":"postgres-jdbc-19348e1c426-2325df8f0983fc11","default-catalog":"BBDD_Proyecto"},"Scripts/2_ NombrePeliculasEdades.sql":{"default-schema":"public","default-datasource":"postgres-jdbc-19348e1c426-2325df8f0983fc11","default-catalog":"postgres"},"Scripts/Script-1.sql":{"default-schema":"public","default-datasource":"postgres-jdbc-19348e1c426-2325df8f0983fc11","default-catalog":"postgres"},"Scripts/Script-2.sql":{"default-datasource":"postgres-jdbc-19348e1c426-2325df8f0983fc11","default-catalog":"BBDD_Proyecto","default-schema":"public"},"Scripts/Script.sql":{"default-schema":"public","default-datasource":"postgres-jdbc-19348e1c426-2325df8f0983fc11","default-catalog":"postgres"},"Scripts/consulta_3.sql":{"default-datasource":"postgres-jdbc-19348e1c426-2325df8f0983fc11","default-catalog":"BBDD_Proyecto","default-schema":"public"},"Scripts/consulta_4.sql":{"default-datasource":"postgres-jdbc-19348e1c426-2325df8f0983fc11","default-catalog":"BBDD_Proyecto","default-schema":"public"},"Scripts/consulta_5.sql":{"default-datasource":"postgres-jdbc-19348e1c426-2325df8f0983fc11","default-catalog":"BBDD_Proyecto","default-schema":"public"},"Scripts/consulta_6.sql":{"default-datasource":"postgres-jdbc-19348e1c426-2325df8f0983fc11","default-catalog":"BBDD_Proyecto","default-schema":"public"}}}